[
    {
        "songname": "Speak to Me",
        "artist": "Pink Floyd",
        "link": "https://www.youtube.com/watch?v=FEacDWPWfJU",
        "image": "song_images/test.png",
        "audio": "song_audio/night.mp3"
    },
    {
        "songname": "Breathe",
        "artist": "Pink Floyd",
        "link": "https://www.youtube.com/watch?v=mrojrDCI02k",
        "image": "song_images/test.png",
        "audio": "song_audio/night.mp3"
    },
    {
        "songname": "On the Run",
        "artist": "Pink Floyd",
        "link": "https://www.youtube.com/watch?v=vVooyS4mG4w",
        "image": "song_images/test.png",
        "audio": "song_audio/night.mp3"
    },
    {
        "songname": "Time",
        "artist": "Pink Floyd",
        "link": "https://www.youtube.com/watch?v=Qr0-7Ds79zo",
        "image": "song_images/test.png",
        "audio": "song_audio/night.mp3"
    },
    {
        "songname": "The Great Gig in the Sky",
        "artist": "Pink Floyd",
        "link": "https://www.youtube.com/watch?v=T13se_2A7c8",
        "image": "song_images/test.png",
        "audio": "song_audio/night.mp3"
    },
    {
        "songname": "Money",
        "artist": "Pink Floyd",
        "link": "https://www.youtube.com/watch?v=JkhX5W7JoWI",
        "image": "song_images/test.png",
        "audio": "song_audio/night.mp3"
    },
    { 
        "songname": "Us and Them",
        "artist": "Pink Floyd",
        "link": "https://www.youtube.com/watch?v=HoLhKJuGhK0",
        "image": "song_images/test.png",
        "audio": "song_audio/night.mp3"
    },
    {
        "songname": "Any Colour You Like",
        "artist": "Pink Floyd",
        "link": "https://www.youtube.com/watch?v=bK7HJvmgFnM",
        "image": "song_images/test.png",
        "audio": "song_audio/night.mp3"
    },
    {
        "songname": "Brain Damage",
        "artist": "Pink Floyd",
        "link": "https://www.youtube.com/watch?v=QFdkM40KOhE",
        "image": "song_images/test.png",
        "audio": "song_audio/night.mp3"
    },
    {
        "songname": "Eclipse",
        "artist": "Pink Floyd",
        "link": "https://www.youtube.com/watch?v=9wjZrswriz0",
        "image": "song_images/test.png",
        "audio": "song_audio/night.mp3"
    },
    {
        "songname": "Sprinter",
        "artist": "Central Cee",
        "link": "https://youtu.be/pSY3i5XHHXo?si=Z6Flr0iPkJMKWf1i",
        "image": "song_images/siOnQHd.png",
        "audio": "song_audio/night.mp3"
    },
    {
        "songname": "One Up",
        "artist": "Central Cee",
        "link": "https://youtu.be/mzpMpj0FHTU?si=XvuiO7ZqnjeTchsC",
        "image": "song_images/siOnQHd.png",
        "audio": "song_audio/night.mp3"
    },
    {
        "songname": "Pinging 6 figures",
        "artist": "Central Cee",
        "link": "https://youtu.be/05uUcFel3ME?si=E-ZrTz0ccFlonNLR",
        "image": "song_images/BOrgmu1.png",
        "audio": "song_audio/night.mp3"
    },
    {
        "songname": "Wants and Needs",
        "artist": "Drake",
        "link": "https://youtu.be/0oBeEnY2CAQ?si=9qEVkY6mReVWXZ39",
        "image": "song_images/QrksXCw.png",
        "audio": "song_audio/night.mp3"
    },
    {
        "songname": "Pine Soul",
        "artist": "Nav",
        "link": "https://youtu.be/4H6P1eUBsDs?si=-mRLcZplyw_haFhZ",
        "image": "song_images/jnyr7mS.png",
        "audio": "song_audio/night.mp3"
    },
    {
        "songname": "Burning",
        "artist": "Mhunco",
        "link": "https://youtu.be/r7jibbi1uL4?si=ckvAFArOi94Bdc-A",
        "image": "song_images/zf2miFl.png",
        "audio": "song_audio/night.mp3"
    },
    {
        "songname": "Pee Pee",
        "artist": "Mhunco",
        "link": "https://youtu.be/7bZq9Kv8bic?si=RX0EL73WlPTrP4jL",
        "image": "song_images/ICeT5Gt.png",
        "audio": "song_audio/night.mp3"
    },
    {
        "songname": "Rap Saved Me",
        "artist": "21 Savage, Offset and Metroboom",
        "link": "https://www.youtube.com/watch?v=LK9rgGmrH7I",
        "image": "song_images/RwdPAaX.png",
        "audio": "song_audio/night.mp3"
    },
    {
        "songname": "Took her to the O",
        "artist": "King Von",
        "link": "https://www.youtube.com/watch?v=hzt31eJTGxo&ab_channel=KingVon",
        "image": "song_images/Okx5aOJ.png",
        "audio": "song_audio/night.mp3"
    },
    {
        "songname": "Too Many nights",
        "artist": "Metroboom, future",
        "link": "https://www.youtube.com/watch?v=NyTkaQHdySM",
        "image": "song_images/artworks-VkCRcGm6T7cx-0-t500x500.png",
        "audio": "song_audio/night.mp3"
    }
]
